predb/PreDBClient.py
predb/__init__.py
predb-1.0.1.dist-info/licenses/LICENSE
predb-1.0.1.dist-info/METADATA
predb-1.0.1.dist-info/WHEEL
predb-1.0.1.dist-info/top_level.txt
predb-1.0.1.dist-info/RECORD
