Metadata-Version: 2.4
Name: predb
Version: 1.0.1
Summary: Python client for PreDB.net API
Author-email: Wellington Estevo <info@propz.de>
License: MIT
Project-URL: Homepage, https://github.com/propz/predb-api-client
Project-URL: Repository, https://github.com/propz/predb-api-client
Project-URL: Issues, https://github.com/propz/predb-api-client/issues
Keywords: predb,api,client,scene,releases
Classifier: Development Status :: 4 - Beta
Classifier: Intended Audience :: Developers
Classifier: License :: OSI Approved :: MIT License
Classifier: Programming Language :: Python :: 3
Classifier: Programming Language :: Python :: 3.7
Classifier: Programming Language :: Python :: 3.8
Classifier: Programming Language :: Python :: 3.9
Classifier: Programming Language :: Python :: 3.10
Classifier: Programming Language :: Python :: 3.11
Classifier: Programming Language :: Python :: 3.12
Classifier: Topic :: Software Development :: Libraries :: Python Modules
Requires-Python: >=3.7
License-File: LICENSE
Requires-Dist: requests>=2.25.0
Requires-Dist: timeago>=1.0.0
Dynamic: license-file
